genstream/__init__.py
genstream/stream.py
genstream-0.0.9.dist-info/DESCRIPTION.rst
genstream-0.0.9.dist-info/METADATA
genstream-0.0.9.dist-info/RECORD
genstream-0.0.9.dist-info/WHEEL
genstream-0.0.9.dist-info/metadata.json
genstream-0.0.9.dist-info/top_level.txt
