Metadata-Version: 2.0
Name: genstream
Version: 0.0.9
Summary: Construct stream pipelines backed by generators
Home-page: https://github.com/lidatong/genstream
Author: lidatong
Author-email: charles.dt.li@gmail.com
License: Unlicense
Keywords: chaining chain generators piping pipes transformations
Platform: UNKNOWN
Requires-Python: >=3.6
Provides-Extra: dev
Requires-Dist: pytest; extra == 'dev'
